py_binance_chain/__init__.py
py_binance_chain/constants.py
py_binance_chain/depthcache.py
py_binance_chain/environment.py
py_binance_chain/exceptions.py
py_binance_chain/http.py
py_binance_chain/messages.py
py_binance_chain/wallet.py
py_binance_chain/websockets.py
py_binance_chain/ledger/__init__.py
py_binance_chain/ledger/client.py
py_binance_chain/ledger/exceptions.py
py_binance_chain/ledger/wallet.py
py_binance_chain/node_rpc/__init__.py
py_binance_chain/node_rpc/http.py
py_binance_chain/node_rpc/pooled_client.py
py_binance_chain/node_rpc/request.py
py_binance_chain/node_rpc/websockets.py
py_binance_chain/protobuf/__init__.py
py_binance_chain/protobuf/dex_pb2.py
py_binance_chain/signing/__init__.py
py_binance_chain/signing/http.py
py_binance_chain/utils/__init__.py
py_binance_chain/utils/encode_utils.py
py_binance_chain/utils/segwit_addr.py
tests/__init__.py
tests/test_client.py
tests/test_depthcache.py
tests/test_environment.py
tests/test_messages.py
tests/test_rpc_client.py
tests/test_rpc_pooled.py
tests/test_rpc_websockets.py
tests/test_signing.py
tests/test_utils.py
tests/test_wallet.py
tests/test_websockets.py
py_binance_chain-0.2.dist-info/LICENSE
py_binance_chain-0.2.dist-info/METADATA
py_binance_chain-0.2.dist-info/WHEEL
py_binance_chain-0.2.dist-info/top_level.txt
py_binance_chain-0.2.dist-info/RECORD
